CHANGELOG
MANIFEST.in
README.rst
setup.cfg
setup.py
tox.ini
devpi_server/__init__.py
devpi_server/__main__.py
devpi_server/auth.py
devpi_server/auth_basic.py
devpi_server/auth_devpi.py
devpi_server/bgserver.py
devpi_server/config.py
devpi_server/extpypi.py
devpi_server/filestore.py
devpi_server/genconfig.py
devpi_server/hookspecs.py
devpi_server/importexport.py
devpi_server/keyfs.py
devpi_server/log.py
devpi_server/main.py
devpi_server/model.py
devpi_server/mythread.py
devpi_server/readonly.py
devpi_server/replica.py
devpi_server/view_auth.py
devpi_server/views.py
devpi_server/cfg/__init__.py
devpi_server/cfg/devpi.service.template
devpi_server/cfg/nginx-devpi.conf.template
devpi_server/cfg/supervisord.conf.template
devpi_server/vendor/__init__.py
devpi_server/vendor/xprocess.py
devpi_server_winfix.egg-info/PKG-INFO
devpi_server_winfix.egg-info/SOURCES.txt
devpi_server_winfix.egg-info/dependency_links.txt
devpi_server_winfix.egg-info/entry_points.txt
devpi_server_winfix.egg-info/not-zip-safe
devpi_server_winfix.egg-info/requires.txt
devpi_server_winfix.egg-info/top_level.txt
test_devpi_server/__init__.py
test_devpi_server/conftest.py
test_devpi_server/example.py
test_devpi_server/functional.py
test_devpi_server/test_auth.py
test_devpi_server/test_bgserver.py
test_devpi_server/test_config.py
test_devpi_server/test_conftest.py
test_devpi_server/test_ctl.py
test_devpi_server/test_extpypi.py
test_devpi_server/test_filestore.py
test_devpi_server/test_genconfig.py
test_devpi_server/test_importexport.py
test_devpi_server/test_keyfs.py
test_devpi_server/test_log.py
test_devpi_server/test_main.py
test_devpi_server/test_model.py
test_devpi_server/test_mythread.py
test_devpi_server/test_permissions.py
test_devpi_server/test_readonly.py
test_devpi_server/test_replica.py
test_devpi_server/test_reqmock.py
test_devpi_server/test_view_auth.py
test_devpi_server/test_views.py