Metadata-Version: 1.1
Name: devpi-server-winfix
Version: 2.5.3a0
Summary: devpi-server-winfix: reliable private and pypi.python.org caching server
Home-page: http://doc.devpi.net
Author: Holger Krekel, Florian Schulze
Author-email: holger@merlinux.eu
License: MIT
Keywords: pypi realtime cache server
Platform: UNKNOWN
Classifier: Development Status :: 5 - Production/Stable
Classifier: Environment :: Web Environment
Classifier: Intended Audience :: Developers
Classifier: Intended Audience :: System Administrators
Classifier: License :: OSI Approved :: MIT License
Classifier: Programming Language :: Python
Classifier: Topic :: Internet :: WWW/HTTP
Classifier: Topic :: Internet :: WWW/HTTP :: WSGI :: Application
Classifier: Programming Language :: Python :: 2.7
Classifier: Programming Language :: Python :: 3.4
Classifier: Programming Language :: Python :: Implementation :: PyPy
